myutils/__init__.py
myutils/logx.py
myutils/transform.py
transelec_d_a_utils_core-0.1.0.dist-info/METADATA
transelec_d_a_utils_core-0.1.0.dist-info/WHEEL
transelec_d_a_utils_core-0.1.0.dist-info/top_level.txt
transelec_d_a_utils_core-0.1.0.dist-info/RECORD
