Metadata-Version: 2.4
Name: transelec-D_A-utils-core
Version: 0.1.0
Summary: Core utilities for data transformation and structured logging.
Home-page: https://github.com/Transelec-repository/mv_utils
Author: Luis Fuenzalida
Author-email: bi-lfuenzalida@transelec.cl
License: MIT
Classifier: Development Status :: 3 - Alpha
Classifier: Intended Audience :: Developers
Classifier: License :: OSI Approved :: MIT License
Classifier: Programming Language :: Python :: 3
Classifier: Programming Language :: Python :: 3.8
Classifier: Programming Language :: Python :: 3.9
Classifier: Programming Language :: Python :: 3.10
Classifier: Programming Language :: Python :: 3.11
Requires-Python: >=3.8
Provides-Extra: bq
Requires-Dist: google-cloud-bigquery>=2.0.0; extra == "bq"
Requires-Dist: google-api-core>=1.0.0; extra == "bq"
Dynamic: author
Dynamic: author-email
Dynamic: classifier
Dynamic: description
Dynamic: description-content-type
Dynamic: home-page
Dynamic: license
Dynamic: provides-extra
Dynamic: requires-python
Dynamic: summary
